chart_builder/__init__.py
chart_builder/__pycache__/__init__.cpython-311.pyc
chart_builder/scripts/__init__.py
chart_builder/scripts/plots.py
chart_builder/scripts/utils.py
chart_builder/scripts/visualization_pipeline.py
chart_builder/scripts/__pycache__/__init__.cpython-311.pyc
chart_builder/scripts/__pycache__/__init__.cpython-312.pyc
chart_builder/scripts/__pycache__/plots.cpython-311.pyc
chart_builder/scripts/__pycache__/plots.cpython-312.pyc
chart_builder/scripts/__pycache__/utils.cpython-311.pyc
chart_builder/scripts/__pycache__/utils.cpython-312.pyc
chart_builder/scripts/__pycache__/visualization_pipeline.cpython-311.pyc
chart_builder/scripts/__pycache__/visualization_pipeline.cpython-312.pyc
chart_builder-0.3.1.dist-info/LICENSE.txt
chart_builder-0.3.1.dist-info/METADATA
chart_builder-0.3.1.dist-info/WHEEL
chart_builder-0.3.1.dist-info/top_level.txt
chart_builder-0.3.1.dist-info/RECORD
