Metadata-Version: 2.1
Name: chart_builder
Version: 0.3.1
Summary: A library for building customizable charts in Python
Home-page: https://github.com/BrandynHamilton/Chart-Builder
Author: Brandyn Hamilton
Author-email: brandynham1120@gmail.com
Classifier: Programming Language :: Python :: 3
Classifier: License :: OSI Approved :: MIT License
Classifier: Operating System :: OS Independent
Requires-Python: >=3.6
License-File: LICENSE.txt
Requires-Dist: pandas
Requires-Dist: numpy
Requires-Dist: plotly
Requires-Dist: kaleido
Requires-Dist: svgwrite
Requires-Dist: python-dotenv
Requires-Dist: colorcet
Requires-Dist: matplotlib
Requires-Dist: nbformat
